colab_code_executor/__init__.py
colab_code_executor/cli.py
colab_code_executor/py.typed
colab_code_executor/server.py
colab_code_executor/test_lro.py
colab_code_executor/test_server.py
colab_code_executor-0.3.5.dist-info/licenses/LICENSE
colab_code_executor-0.3.5.dist-info/METADATA
colab_code_executor-0.3.5.dist-info/WHEEL
colab_code_executor-0.3.5.dist-info/entry_points.txt
colab_code_executor-0.3.5.dist-info/top_level.txt
colab_code_executor-0.3.5.dist-info/RECORD
