Metadata-Version: 2.4
Name: colab-code-executor
Version: 0.3.5
Summary: FastAPI server for remote Jupyter kernel management with code execution capabilities
Author-email: Gonzalo Gasca Meza <gascagonzalo@gmail.com>
Maintainer-email: Gonzalo Gasca Meza <gascagonzalo@gmail.com>
License: MIT
Project-URL: Homepage, https://github.com/codeexec/colab
Project-URL: Repository, https://github.com/codeexec/colab
Project-URL: Issues, https://github.com/codeexec/colab/issues
Keywords: jupyter,kernel,fastapi,code-execution,proxy,colab
Classifier: Development Status :: 3 - Alpha
Classifier: Intended Audience :: Developers
Classifier: License :: OSI Approved :: MIT License
Classifier: Programming Language :: Python :: 3
Classifier: Programming Language :: Python :: 3.10
Classifier: Programming Language :: Python :: 3.11
Classifier: Programming Language :: Python :: 3.12
Classifier: Framework :: FastAPI
Classifier: Topic :: Software Development :: Libraries :: Python Modules
Requires-Python: >=3.10
License-File: LICENSE
Requires-Dist: fastapi>=0.100.0
Requires-Dist: uvicorn>=0.20.0
Requires-Dist: httpx>=0.24.0
Requires-Dist: websockets>=11.0
Requires-Dist: pydantic>=2.0.0
Requires-Dist: pydantic-settings>=2.0.0
Provides-Extra: dev
Requires-Dist: pytest>=7.0.0; extra == "dev"
Requires-Dist: pytest-asyncio>=0.21.0; extra == "dev"
Requires-Dist: pytest-mock>=3.10.0; extra == "dev"
Requires-Dist: pytest-cov>=4.0.0; extra == "dev"
Dynamic: license-file
